surferrr/__init__.py
surferrr/base/base_browser.py
surferrr/browser/chrome.py
surferrr-0.1.0.dist-info/LICENSE
surferrr-0.1.0.dist-info/WHEEL
surferrr-0.1.0.dist-info/METADATA
surferrr-0.1.0.dist-info/RECORD
