Metadata-Version: 2.1
Name: surferrr
Version: 0.1.0
Summary: Control web browser like a surfer.
License: MIT
Author: Takeru Saito
Author-email: takelushi@gmail.com
Requires-Python: >=3.7,<4.0
Classifier: License :: OSI Approved :: MIT License
Classifier: Programming Language :: Python :: 3
Classifier: Programming Language :: Python :: 3.7
Classifier: Programming Language :: Python :: 3.8
Classifier: Programming Language :: Python :: 3.9
Requires-Dist: selenium (>=3)
